LICENSE
MANIFEST.in
README
setup.py
datagrid/__init__.py
datagrid/grids.py
datagrid/tests.py
datagrid/templates/datagrid/as_csv.csv
datagrid/templates/datagrid/as_pdf.pdf
datagrid/templates/datagrid/cell.html
datagrid/templates/datagrid/column_header.html
datagrid/templates/datagrid/datagrid.html
datagrid/templates/datagrid/get_csv_link.html
datagrid/templates/datagrid/get_filter_form.html
datagrid/templates/datagrid/get_pdf_link.html
datagrid/templates/datagrid/get_search_form.html
datagrid/templates/datagrid/listview.html
datagrid/templates/datagrid/pagination_size_frag.html
datagrid/templates/datagrid/paginator.html
datagrid/templatetags/__init__.py
datagrid/templatetags/datagrid.py
django_datagrid.egg-info/PKG-INFO
django_datagrid.egg-info/SOURCES.txt
django_datagrid.egg-info/dependency_links.txt
django_datagrid.egg-info/not-zip-safe
django_datagrid.egg-info/top_level.txt
example/__init__.py
example/__init__.pyc
example/manage.py
example/settings.py
example/settings.pyc
example/urls.py
example/blog_grids/.project
example/blog_grids/.pydevproject
example/blog_grids/__init__.py
example/blog_grids/models.py
example/blog_grids/tests.py
example/blog_grids/views.py
example/blog_grids/templates/blog_grid/blog_grid.html
example/blogango/__init__.py
example/blogango/__init__.pyc
example/blogango/admin.py
example/blogango/akismet.py
example/blogango/context_processors.py
example/blogango/feeds.py
example/blogango/forms.py
example/blogango/models.py
example/blogango/search.py
example/blogango/urls.py
example/blogango/views.py
example/blogango/conf/__init__.py
example/blogango/conf/settings.py
example/blogango/fixtures/initial_data.json
example/blogango/templates/b-404.html
example/blogango/templates/b-500.html
example/blogango/templates/base.html
example/blogango/templates/entry_footer.html
example/blogango/templates/search.html
example/blogango/templates/blogango/archive_view.html
example/blogango/templates/blogango/author.html
example/blogango/templates/blogango/blogroll.html
example/blogango/templates/blogango/comment.html
example/blogango/templates/blogango/commentcontrols.html
example/blogango/templates/blogango/create.html
